Practica3Active/Practica3/src/counter.v
module counter #(
	parameter n=11
	)(
	input wire clk, rst, 
	output reg en
	);
	
	integer count; // variable de la cuenta 
	
	always @(posedge clk or posedge rst) begin 
		if (rst) begin
			count = 0;
			en = 1'b0;
		end else begin 
		if (count == n ) begin 
			en = 1'b1;// porque ya está mi cuenta maxima y quiero hacer una nueva iteracion 	
			count = 0;
		end else begin 		   
		en = 1'b0;
		count = count +1;
		
	end
end  
end
endmodule

Practica3Active/Practica3/src/tbs.v
`timescale 1ns / 1ps

module register_tb;

    // Parámetros
    localparam n = 32;
    localparam INIT_VAL = 32'b00000000000100000000000000000000;

    // Señales
    reg clk;
    reg rst;
    reg en;
    reg [n-1:0] d;
    wire [n-1:0] q;

    // Instancia del módulo bajo prueba
    register #(.n(n), .INIT_VAL(INIT_VAL)) uut (
        .clk(clk),
        .rst(rst),
        .en(en),
        .d(d),
        .q(q)
    );

    // Generador de reloj: periodo de 10 ns
    initial clk = 0;
    always #5 clk = ~clk;

    // Secuencia de prueba
    initial begin
        $display("Inicio de simulación");
        $monitor("Tiempo=%0t | rst=%b en=%b d=%h q=%h", $time, rst, en, d, q);

        // Inicialización
        rst = 1; en = 0; d = 32'hDEADBEEF;
        #12;  // Espera más de un ciclo de reloj

        // Desactiva reset, espera sin enable
        rst = 0;
        #10;

        // Activa enable y carga nuevo dato
        en = 1; d = 32'hCAFEBABE;
        #10;

        // Cambia dato con enable activo
        d = 32'h12345678;
        #10;

        // Desactiva enable, dato no debe cambiar
        en = 0; d = 32'hFFFFFFFF;
        #10;

        // Activa reset nuevamente
        rst = 1;
        #8;

        // Finaliza simulación
        $finish;
    end

endmodule		

module tb_counter;

    // Parámetros
    parameter n = 11;

    // Señales
    reg clk;
    reg rst;
    wire en;

    // Instancia del módulo bajo prueba (DUT)
    counter #(.n(n)) dut (
        .clk(clk),
        .rst(rst),
        .en(en)
    );

    // Generador de reloj: periodo de 10 ns (100 MHz)
    initial clk = 0;
    always #5 clk = ~clk;

    // Estímulos
    initial begin
        $display("Inicio del testbench");
        $dumpfile("tb_counter.vcd");     // Para simulación con GTKWave
        $dumpvars(0, tb_counter);

        // Reset inicial
        rst = 1;
        #20;
        rst = 0;

        // Ejecutar por varios ciclos
        #500;

        // Finalizar simulación
        $display("Fin del testbench");
        $finish;
    end

endmodule

Practica3Active/Practica3/tb_counter.vcd
$date
Wed Oct  8 21:33:20 2025
$end
$version
Aldec HDL Simulator Version 15.0.261
$end
$timescale
1 ps
$end

$scope module tb_counter $end
$var wire 1 ! en $end
$var reg 1 " clk $end
$var reg 1 # rst $end
$var parameter 32 $ n [31:0] $end

$scope module dut $end
$var wire 1 % clk $end
$var wire 1 & rst $end
$var reg 1 ' en $end
$var integer 32 ( count $end
$var parameter 32 ) n [31:0] $end
$upscope $end

$upscope $end

$enddefinitions $end
$dumpvars
0!
0"
1#
b1011 $
0%
1&
0'
b0 (
b1011 )
$end
#5000
1"
1%
#10000
0"
0%
#15000
1"
1%
#20000
0#
0"
0%
0&
#25000
1"
1%
b1 (
#30000
0"
0%
#35000
1"
1%
b10 (
#40000
0"
0%
#45000
1"
1%
b11 (
#50000
0"
0%
#55000
1"
1%
b100 (
#60000
0"
0%
#65000
1"
1%
b101 (
#70000
0"
0%
#75000
1"
1%
b110 (
#80000
0"
0%
#85000
1"
1%
b111 (
#90000
0"
0%
#95000
1"
1%
b1000 (
#100000
0"
0%
#105000
1"
1%
b1001 (
#110000
0"
0%
#115000
1"
1%
b1010 (
#120000
0"
0%
#125000
1"
1%
b1011 (
#130000
0"
0%
#135000
1"
1%
1'
b0 (
1!
#140000
0"
0%
#145000
1"
1%
0'
b1 (
0!
#150000
0"
0%
#155000
1"
1%
b10 (
#160000
0"
0%
#165000
1"
1%
b11 (
#170000
0"
0%
#175000
1"
1%
b100 (
#180000
0"
0%
#185000
1"
1%
b101 (
#190000
0"
0%
#195000
1"
1%
b110 (
#200000
0"
0%
#205000
1"
1%
b111 (
#210000
0"
0%
#215000
1"
1%
b1000 (
#220000
0"
0%
#225000
1"
1%
b1001 (
#230000
0"
0%
#235000
1"
1%
b1010 (
#240000
0"
0%
#245000
1"
1%
b1011 (
#250000
0"
0%
#255000
1"
1%
1'
b0 (
1!
#260000
0"
0%
#265000
1"
1%
0'
b1 (
0!
#270000
0"
0%
#275000
1"
1%
b10 (
#280000
0"
0%
#285000
1"
1%
b11 (
#290000
0"
0%
#295000
1"
1%
b100 (
#300000
0"
0%
#305000
1"
1%
b101 (
#310000
0"
0%
#315000
1"
1%
b110 (
#320000
0"
0%
#325000
1"
1%
b111 (
#330000
0"
0%
#335000
1"
1%
b1000 (
#340000
0"
0%
#345000
1"
1%
b1001 (
#350000
0"
0%
#355000
1"
1%
b1010 (
#360000
0"
0%
#365000
1"
1%
b1011 (
#370000
0"
0%
#375000
1"
1%
1'
b0 (
1!
#380000
0"
0%
#385000
1"
1%
0'
b1 (
0!
#390000
0"
0%
#395000
1"
1%
b10 (
#400000
0"
0%
#405000
1"
1%
b11 (
#410000
0"
0%
#415000
1"
1%
b100 (
#420000
0"
0%
#425000
1"
1%
b101 (
#430000
0"
0%
#435000
1"
1%
b110 (
#440000
0"
0%
#445000
1"
1%
b111 (
#450000
0"
0%
#455000
1"
1%
b1000 (
#460000
0"
0%
#465000
1"
1%
b1001 (
#470000
0"
0%
#475000
1"
1%
b1010 (
#480000
0"
0%
#485000
1"
1%
b1011 (
#490000
0"
0%
#495000
1"
1%
1'
b0 (
1!
#500000
0"
0%
#505000
1"
1%
0'
b1 (
0!
#510000
0"
0%
#515000
1"
1%
b10 (
